{"cameraMode":{"drawMode":0,"name":"Shaded","section":"Shading Mode"},"sceneLighting":true,"audioPlay":false,"sceneViewState":{"showFog":true,"showMaterialUpdate":false,"showSkybox":true,"showFlares":true,"showImageEffects":true,"showParticleSystems":true},"in2DMode":false,"pivot":{"x":-3.3081722259521486,"y":-1.699925184249878,"z":22.281251907348634},"rotation":{"x":-0.061549682170152667,"y":0.0843350738286972,"z":-0.005218982230871916,"w":-0.9945237040519714},"size":28.527259826660158,"orthographic":false}